HectareaPES/__init__.py
HectareaPES-4.20.68.99.99.99.dist-info/METADATA
HectareaPES-4.20.68.99.99.99.dist-info/WHEEL
HectareaPES-4.20.68.99.99.99.dist-info/top_level.txt
HectareaPES-4.20.68.99.99.99.dist-info/RECORD
