Metadata-Version: 2.1
Name: HectareaPES
Version: 4.20.68.99.99.99
Summary: Hectarea Pizza Encryption Standard
Home-page: https://hectarea.netlify.app/
Author: Héctarea
Author-email: gonzalez.craqenll@gmail.com
License: MIT
Download-URL: https://github.com/Hectarea/Hectarea-PES/archive/refs/tags/69.4.19.99.tar.gz
Keywords: Encryption,Pizza,Hectarea,Panera
Platform: UNKNOWN
